[{"time":"00:00","exch_uk":829.0,"exch_es":240.0,"exch_it":-3784.0,"exch_ch":-2934.0,"exch_de_be":3278.0,"co2_rate":58.0},{"time":"01:30","exch_uk":456.0,"exch_es":1516.0,"exch_it":-3628.0,"exch_ch":-3200.0,"exch_de_be":3255.0,"co2_rate":45.0},{"time":"02:45","exch_uk":262.0,"exch_es":2697.0,"exch_it":-3911.0,"exch_ch":-3200.0,"exch_de_be":2219.0,"co2_rate":46.0},{"time":"03:00","exch_uk":289.0,"exch_es":2778.0,"exch_it":-3974.0,"exch_ch":-3200.0,"exch_de_be":2216.0,"co2_rate":46.0},{"time":"03:30","exch_uk":289.0,"exch_es":2778.0,"exch_it":-3984.0,"exch_ch":-3200.0,"exch_de_be":2009.0,"co2_rate":45.0},{"time":"05:15","exch_uk":577.0,"exch_es":2800.0,"exch_it":-3984.0,"exch_ch":-2622.0,"exch_de_be":1017.0,"co2_rate":47.0},{"time":"06:30","exch_uk":1462.0,"exch_es":2350.0,"exch_it":-3517.0,"exch_ch":-2465.0,"exch_de_be":649.0,"co2_rate":57.0},{"time":"09:45","exch_uk":200.0,"exch_es":2200.0,"exch_it":-1028.0,"exch_ch":-584.0,"exch_de_be":-392.0,"co2_rate":55.0},{"time":"13:00","exch_uk":-1381.0,"exch_es":2050.0,"exch_it":-1691.0,"exch_ch":-3200.0,"exch_de_be":1687.0,"co2_rate":52.0},{"time":"13:45","exch_uk":-1381.0,"exch_es":2050.0,"exch_it":-2923.0,"exch_ch":-3200.0,"exch_de_be":1611.0,"co2_rate":51.0},{"time":"15:00","exch_uk":-1357.0,"exch_es":1100.0,"exch_it":-2425.0,"exch_ch":-3200.0,"exch_de_be":-1884.0,"co2_rate":49.0},{"time":"15:15","exch_uk":-1357.0,"exch_es":1100.0,"exch_it":-2241.0,"exch_ch":-3200.0,"exch_de_be":-2132.0,"co2_rate":53.0},{"time":"16:45","exch_uk":-709.0,"exch_es":1100.0,"exch_it":-2385.0,"exch_ch":-3200.0,"exch_de_be":-3273.0,"co2_rate":58.0},{"time":"17:00","exch_uk":-1785.0,"exch_es":1100.0,"exch_it":-2230.0,"exch_ch":-2714.0,"exch_de_be":-2493.0,"co2_rate":59.0},{"time":"21:15","exch_uk":-296.0,"exch_es":-2044.0,"exch_it":-2033.0,"exch_ch":-1069.0,"exch_de_be":-1069.0,"co2_rate":56.0},{"time":"22:45","exch_uk":-21.0,"exch_es":940.0,"exch_it":-2281.0,"exch_ch":-3057.0,"exch_de_be":221.0,"co2_rate":58.0},{"time":"23:15","exch_uk":128.0,"exch_es":1555.0,"exch_it":-2806.0,"exch_ch":-3122.0,"exch_de_be":108.0,"co2_rate":58.0},{"time":"23:45","exch_uk":128.0,"exch_es":1555.0,"exch_it":-2718.0,"exch_ch":-3112.0,"exch_de_be":122.0,"co2_rate":57.0},{"time":"00:30","exch_uk":829.0,"exch_es":240.0,"exch_it":-3549.0,"exch_ch":-2934.0,"exch_de_be":3551.0,"co2_rate":48.0},{"time":"04:45","exch_uk":-119.0,"exch_es":2800.0,"exch_it":-3983.0,"exch_ch":-3198.0,"exch_de_be":1663.0,"co2_rate":46.0},{"time":"07:00","exch_uk":1644.0,"exch_es":2350.0,"exch_it":-3561.0,"exch_ch":-1024.0,"exch_de_be":-159.0,"co2_rate":57.0},{"time":"07:15","exch_uk":1644.0,"exch_es":2350.0,"exch_it":-3352.0,"exch_ch":-1024.0,"exch_de_be":255.0,"co2_rate":57.0},{"time":"08:00","exch_uk":634.0,"exch_es":936.0,"exch_it":-647.0,"exch_ch":557.0,"exch_de_be":-974.0,"co2_rate":56.0},{"time":"08:30","exch_uk":634.0,"exch_es":936.0,"exch_it":-983.0,"exch_ch":557.0,"exch_de_be":-51.0,"co2_rate":56.0},{"time":"09:00","exch_uk":200.0,"exch_es":2200.0,"exch_it":-1164.0,"exch_ch":-584.0,"exch_de_be":122.0,"co2_rate":56.0},{"time":"10:30","exch_uk":-84.0,"exch_es":2200.0,"exch_it":-1739.0,"exch_ch":-1208.0,"exch_de_be":251.0,"co2_rate":54.0},{"time":"10:45","exch_uk":-84.0,"exch_es":2200.0,"exch_it":-1853.0,"exch_ch":-1208.0,"exch_de_be":221.0,"co2_rate":52.0},{"time":"12:30","exch_uk":-549.0,"exch_es":2050.0,"exch_it":-550.0,"exch_ch":-2798.0,"exch_de_be":638.0,"co2_rate":54.0},{"time":"12:45","exch_uk":-549.0,"exch_es":2050.0,"exch_it":-656.0,"exch_ch":-2798.0,"exch_de_be":450.0,"co2_rate":53.0},{"time":"13:15","exch_uk":-1381.0,"exch_es":2050.0,"exch_it":-1818.0,"exch_ch":-3200.0,"exch_de_be":1687.0,"co2_rate":52.0},{"time":"13:30","exch_uk":-1381.0,"exch_es":2050.0,"exch_it":-2569.0,"exch_ch":-3200.0,"exch_de_be":1676.0,"co2_rate":50.0},{"time":"14:00","exch_uk":-1568.0,"exch_es":2050.0,"exch_it":-2484.0,"exch_ch":-3200.0,"exch_de_be":520.0,"co2_rate":50.0},{"time":"16:30","exch_uk":-709.0,"exch_es":1100.0,"exch_it":-2502.0,"exch_ch":-3200.0,"exch_de_be":-3082.0,"co2_rate":57.0},{"time":"17:45","exch_uk":-1785.0,"exch_es":1100.0,"exch_it":-1891.0,"exch_ch":-2715.0,"exch_de_be":-1896.0,"co2_rate":58.0},{"time":"21:45","exch_uk":-296.0,"exch_es":-2044.0,"exch_it":-1971.0,"exch_ch":-1069.0,"exch_de_be":-1484.0,"co2_rate":57.0},{"time":"22:00","exch_uk":-21.0,"exch_es":940.0,"exch_it":-2690.0,"exch_ch":-3088.0,"exch_de_be":-1037.0,"co2_rate":57.0},{"time":"22:15","exch_uk":-21.0,"exch_es":940.0,"exch_it":-2855.0,"exch_ch":-3088.0,"exch_de_be":-667.0,"co2_rate":57.0},{"time":"23:00","exch_uk":128.0,"exch_es":1555.0,"exch_it":-2686.0,"exch_ch":-3122.0,"exch_de_be":164.0,"co2_rate":58.0},{"time":"00:45","exch_uk":829.0,"exch_es":240.0,"exch_it":-3750.0,"exch_ch":-2934.0,"exch_de_be":3471.0,"co2_rate":47.0},{"time":"02:15","exch_uk":262.0,"exch_es":2697.0,"exch_it":-3903.0,"exch_ch":-3200.0,"exch_de_be":2639.0,"co2_rate":46.0},{"time":"03:45","exch_uk":289.0,"exch_es":2778.0,"exch_it":-3984.0,"exch_ch":-3200.0,"exch_de_be":1810.0,"co2_rate":46.0},{"time":"04:15","exch_uk":-119.0,"exch_es":2800.0,"exch_it":-3984.0,"exch_ch":-3198.0,"exch_de_be":1970.0,"co2_rate":46.0},{"time":"05:00","exch_uk":577.0,"exch_es":2800.0,"exch_it":-3984.0,"exch_ch":-2622.0,"exch_de_be":1012.0,"co2_rate":46.0},{"time":"10:15","exch_uk":-84.0,"exch_es":2200.0,"exch_it":-1349.0,"exch_ch":-1239.0,"exch_de_be":425.0,"co2_rate":55.0},{"time":"11:00","exch_uk":-246.0,"exch_es":2050.0,"exch_it":-1046.0,"exch_ch":-2238.0,"exch_de_be":771.0,"co2_rate":53.0},{"time":"11:30","exch_uk":-246.0,"exch_es":2050.0,"exch_it":-1477.0,"exch_ch":-2288.0,"exch_de_be":1178.0,"co2_rate":53.0},{"time":"12:15","exch_uk":-549.0,"exch_es":2050.0,"exch_it":-815.0,"exch_ch":-2798.0,"exch_de_be":914.0,"co2_rate":54.0},{"time":"14:30","exch_uk":-1568.0,"exch_es":2050.0,"exch_it":-2934.0,"exch_ch":-3200.0,"exch_de_be":440.0,"co2_rate":50.0},{"time":"17:15","exch_uk":-1785.0,"exch_es":1100.0,"exch_it":-2171.0,"exch_ch":-2714.0,"exch_de_be":-2332.0,"co2_rate":58.0},{"time":"17:30","exch_uk":-1785.0,"exch_es":1100.0,"exch_it":-2223.0,"exch_ch":-2715.0,"exch_de_be":-2126.0,"co2_rate":59.0},{"time":"18:00","exch_uk":-1371.0,"exch_es":2087.0,"exch_it":145.0,"exch_ch":-1484.0,"exch_de_be":-3925.0,"co2_rate":58.0},{"time":"18:30","exch_uk":-1371.0,"exch_es":2087.0,"exch_it":839.0,"exch_ch":-1484.0,"exch_de_be":-2487.0,"co2_rate":56.0},{"time":"18:45","exch_uk":-1371.0,"exch_es":2087.0,"exch_it":978.0,"exch_ch":-1484.0,"exch_de_be":-2285.0,"co2_rate":56.0},{"time":"19:00","exch_uk":-1076.0,"exch_es":-712.0,"exch_it":1283.0,"exch_ch":-1346.0,"exch_de_be":-920.0,"co2_rate":56.0},{"time":"21:30","exch_uk":-296.0,"exch_es":-2044.0,"exch_it":-1839.0,"exch_ch":-1069.0,"exch_de_be":-1172.0,"co2_rate":56.0},{"time":"22:30","exch_uk":-21.0,"exch_es":940.0,"exch_it":-2081.0,"exch_ch":-3057.0,"exch_de_be":-31.0,"co2_rate":58.0},{"time":"00:15","exch_uk":829.0,"exch_es":240.0,"exch_it":-3541.0,"exch_ch":-2934.0,"exch_de_be":3585.0,"co2_rate":54.0},{"time":"01:00","exch_uk":456.0,"exch_es":1516.0,"exch_it":-3627.0,"exch_ch":-3200.0,"exch_de_be":3248.0,"co2_rate":46.0},{"time":"01:15","exch_uk":456.0,"exch_es":1516.0,"exch_it":-3810.0,"exch_ch":-3200.0,"exch_de_be":3332.0,"co2_rate":46.0},{"time":"02:00","exch_uk":262.0,"exch_es":2697.0,"exch_it":-3662.0,"exch_ch":-3200.0,"exch_de_be":2771.0,"co2_rate":45.0},{"time":"05:45","exch_uk":577.0,"exch_es":2800.0,"exch_it":-3872.0,"exch_ch":-2622.0,"exch_de_be":1079.0,"co2_rate":50.0},{"time":"06:15","exch_uk":1462.0,"exch_es":2350.0,"exch_it":-2900.0,"exch_ch":-2465.0,"exch_de_be":810.0,"co2_rate":55.0},{"time":"06:45","exch_uk":1462.0,"exch_es":2350.0,"exch_it":-2966.0,"exch_ch":-2465.0,"exch_de_be":643.0,"co2_rate":58.0},{"time":"07:30","exch_uk":1644.0,"exch_es":2350.0,"exch_it":-3539.0,"exch_ch":-1024.0,"exch_de_be":95.0,"co2_rate":57.0},{"time":"07:45","exch_uk":1644.0,"exch_es":2350.0,"exch_it":-3042.0,"exch_ch":-1024.0,"exch_de_be":-17.0,"co2_rate":57.0},{"time":"08:45","exch_uk":634.0,"exch_es":936.0,"exch_it":-790.0,"exch_ch":557.0,"exch_de_be":-138.0,"co2_rate":56.0},{"time":"09:30","exch_uk":200.0,"exch_es":2200.0,"exch_it":-991.0,"exch_ch":-584.0,"exch_de_be":-285.0,"co2_rate":55.0},{"time":"10:00","exch_uk":-84.0,"exch_es":2200.0,"exch_it":-1095.0,"exch_ch":-1239.0,"exch_de_be":302.0,"co2_rate":54.0},{"time":"14:15","exch_uk":-1568.0,"exch_es":2050.0,"exch_it":-2544.0,"exch_ch":-3200.0,"exch_de_be":512.0,"co2_rate":50.0},{"time":"15:30","exch_uk":-1357.0,"exch_es":1100.0,"exch_it":-2426.0,"exch_ch":-3200.0,"exch_de_be":-2570.0,"co2_rate":53.0},{"time":"15:45","exch_uk":-1357.0,"exch_es":1100.0,"exch_it":-2290.0,"exch_ch":-3200.0,"exch_de_be":-2722.0,"co2_rate":55.0},{"time":"16:00","exch_uk":-709.0,"exch_es":1100.0,"exch_it":-2627.0,"exch_ch":-3200.0,"exch_de_be":-2936.0,"co2_rate":55.0},{"time":"16:15","exch_uk":-709.0,"exch_es":1100.0,"exch_it":-2430.0,"exch_ch":-3200.0,"exch_de_be":-3014.0,"co2_rate":56.0},{"time":"19:45","exch_uk":-1076.0,"exch_es":-713.0,"exch_it":1311.0,"exch_ch":-1346.0,"exch_de_be":-1023.0,"co2_rate":55.0},{"time":"20:00","exch_uk":-1121.0,"exch_es":-2488.0,"exch_it":1491.0,"exch_ch":-466.0,"exch_de_be":-2210.0,"co2_rate":55.0},{"time":"20:30","exch_uk":-1121.0,"exch_es":-2488.0,"exch_it":1689.0,"exch_ch":-466.0,"exch_de_be":-2740.0,"co2_rate":56.0},{"time":"23:30","exch_uk":128.0,"exch_es":1555.0,"exch_it":-2723.0,"exch_ch":-3112.0,"exch_de_be":495.0,"co2_rate":57.0},{"time":"01:45","exch_uk":456.0,"exch_es":1516.0,"exch_it":-3763.0,"exch_ch":-3200.0,"exch_de_be":3105.0,"co2_rate":44.0},{"time":"02:30","exch_uk":262.0,"exch_es":2697.0,"exch_it":-3910.0,"exch_ch":-3200.0,"exch_de_be":2679.0,"co2_rate":46.0},{"time":"03:15","exch_uk":289.0,"exch_es":2778.0,"exch_it":-3984.0,"exch_ch":-3200.0,"exch_de_be":2088.0,"co2_rate":46.0},{"time":"04:00","exch_uk":-119.0,"exch_es":2800.0,"exch_it":-3983.0,"exch_ch":-3198.0,"exch_de_be":2043.0,"co2_rate":45.0},{"time":"04:30","exch_uk":-119.0,"exch_es":2800.0,"exch_it":-3983.0,"exch_ch":-3198.0,"exch_de_be":1689.0,"co2_rate":46.0},{"time":"05:30","exch_uk":577.0,"exch_es":2800.0,"exch_it":-3984.0,"exch_ch":-2622.0,"exch_de_be":1050.0,"co2_rate":48.0},{"time":"06:00","exch_uk":1462.0,"exch_es":2350.0,"exch_it":-3321.0,"exch_ch":-2465.0,"exch_de_be":865.0,"co2_rate":52.0},{"time":"08:15","exch_uk":634.0,"exch_es":936.0,"exch_it":-1147.0,"exch_ch":557.0,"exch_de_be":-407.0,"co2_rate":56.0},{"time":"09:15","exch_uk":200.0,"exch_es":2200.0,"exch_it":-1173.0,"exch_ch":-584.0,"exch_de_be":49.0,"co2_rate":56.0},{"time":"11:15","exch_uk":-246.0,"exch_es":2050.0,"exch_it":-1420.0,"exch_ch":-2238.0,"exch_de_be":1096.0,"co2_rate":53.0},{"time":"11:45","exch_uk":-246.0,"exch_es":2050.0,"exch_it":-1490.0,"exch_ch":-2288.0,"exch_de_be":1113.0,"co2_rate":53.0},{"time":"12:00","exch_uk":-549.0,"exch_es":2050.0,"exch_it":-785.0,"exch_ch":-2798.0,"exch_de_be":905.0,"co2_rate":52.0},{"time":"14:45","exch_uk":-1568.0,"exch_es":2050.0,"exch_it":-3055.0,"exch_ch":-3200.0,"exch_de_be":478.0,"co2_rate":49.0},{"time":"18:15","exch_uk":-1371.0,"exch_es":2087.0,"exch_it":229.0,"exch_ch":-1484.0,"exch_de_be":-3270.0,"co2_rate":57.0},{"time":"19:15","exch_uk":-1076.0,"exch_es":-713.0,"exch_it":1022.0,"exch_ch":-1346.0,"exch_de_be":-684.0,"co2_rate":55.0},{"time":"19:30","exch_uk":-1076.0,"exch_es":-713.0,"exch_it":1143.0,"exch_ch":-1346.0,"exch_de_be":-535.0,"co2_rate":55.0},{"time":"20:15","exch_uk":-1121.0,"exch_es":-2488.0,"exch_it":1591.0,"exch_ch":-466.0,"exch_de_be":-2582.0,"co2_rate":55.0},{"time":"20:45","exch_uk":-1121.0,"exch_es":-2488.0,"exch_it":1448.0,"exch_ch":-466.0,"exch_de_be":-3001.0,"co2_rate":56.0},{"time":"21:00","exch_uk":-296.0,"exch_es":-2044.0,"exch_it":-1398.0,"exch_ch":-1069.0,"exch_de_be":-1545.0,"co2_rate":56.0}]